LICENSE.txt
MANIFEST.in
README.rst
requirements.txt
setup.cfg
setup.py
pycoalescence/__init__.py
pycoalescence/coalescence_tree.py
pycoalescence/dispersal_simulation.py
pycoalescence/fragment_config.py
pycoalescence/fragments.py
pycoalescence/future_except.py
pycoalescence/helper.py
pycoalescence/hpc_setup.py
pycoalescence/installer.py
pycoalescence/landscape.py
pycoalescence/landscape_metrics.py
pycoalescence/map.py
pycoalescence/merger.py
pycoalescence/patched_landscape.py
pycoalescence/simulation.py
pycoalescence/spatial_algorithms.py
pycoalescence/sqlite_connection.py
pycoalescence/system_operations.py
pycoalescence.egg-info/PKG-INFO
pycoalescence.egg-info/SOURCES.txt
pycoalescence.egg-info/dependency_links.txt
pycoalescence.egg-info/not-zip-safe
pycoalescence.egg-info/requires.txt
pycoalescence.egg-info/top_level.txt
pycoalescence/lib/CMakeLists.txt
pycoalescence/lib/LandscapeMetricsCalculator.cpp
pycoalescence/lib/LandscapeMetricsCalculator.h
pycoalescence/lib/Makefile.in
pycoalescence/lib/PyLogger.cpp
pycoalescence/lib/PyLogger.h
pycoalescence/lib/PyLogging.cpp
pycoalescence/lib/PyLogging.h
pycoalescence/lib/aclocal.m4
pycoalescence/lib/configure.ac
pycoalescence/lib/depends_default
pycoalescence/lib/necsim.cpp
pycoalescence/lib/necsim.h
pycoalescence/lib/CMakeFiles/3.15.3/CompilerIdCXX/CMakeCXXCompilerId.cpp
pycoalescence/lib/cmake/FindGDAL2.cmake
pycoalescence/lib/cmake/Findsqlite3.cmake
pycoalescence/lib/m4/ax_cxx_compile_stdcxx.m4
pycoalescence/lib/m4/ax_cxx_compile_stdcxx_14.m4
pycoalescence/lib/m4/boost.m4
pycoalescence/lib/necsim/ActivityMap.cpp
pycoalescence/lib/necsim/ActivityMap.h
pycoalescence/lib/necsim/AnalyticalSpeciesAbundancesHandler.cpp
pycoalescence/lib/necsim/AnalyticalSpeciesAbundancesHandler.h
pycoalescence/lib/necsim/Cell.cpp
pycoalescence/lib/necsim/Cell.h
pycoalescence/lib/necsim/Community.cpp
pycoalescence/lib/necsim/Community.h
pycoalescence/lib/necsim/ConfigParser.cpp
pycoalescence/lib/necsim/ConfigParser.h
pycoalescence/lib/necsim/DataMask.cpp
pycoalescence/lib/necsim/DataMask.h
pycoalescence/lib/necsim/DataPoint.cpp
pycoalescence/lib/necsim/DataPoint.h
pycoalescence/lib/necsim/DispersalCoordinator.cpp
