Metadata-Version: 2.1
Name: pycoalescence
Version: 1.2.8.post3
Summary: A spatially explicit neutral ecology simulator using coalescence methods
Home-page: http://pycoalescence.readthedocs.io/
Author: Sam Thompson
Author-email: thompsonsed@gmail.com
License: MIT
Keywords: neutral simulation ecology spatially explicit
Platform: UNKNOWN
Classifier: Development Status :: 4 - Beta
Classifier: License :: OSI Approved :: MIT License
Classifier: Operating System :: MacOS
Classifier: Operating System :: MacOS :: MacOS X
Classifier: Operating System :: Microsoft :: Windows :: Windows 10
Classifier: Operating System :: POSIX
Classifier: Programming Language :: C++
Classifier: Programming Language :: Python :: 2.7
Classifier: Programming Language :: Python :: 3.6
Classifier: Programming Language :: Python :: 3.7
Classifier: Programming Language :: Python :: 3
Classifier: Programming Language :: Python :: Implementation :: CPython
Classifier: Topic :: Scientific/Engineering
Classifier: Intended Audience :: Science/Research
Classifier: Natural Language :: English
Provides-Extra: plotting
Provides-Extra: scipy
